pwa/__init__.py
pwa/apps.py
pwa/defaults.py
pwa/urls.py
pwa/views.py
pwa/static/pwa/images/dino.gif
pwa/static/pwa/images/icons/128x128.png
pwa/static/pwa/images/icons/144x144.png
pwa/static/pwa/images/icons/152x152.png
pwa/static/pwa/images/icons/192x192.png
pwa/static/pwa/images/icons/384x384.png
pwa/static/pwa/images/icons/512x512.png
pwa/static/pwa/images/icons/72x72.png
pwa/static/pwa/images/icons/96x96.png
pwa/static/pwa/images/icons/favicon.ico
pwa/templates/pwa/meta_script.html
pwa/templates/pwa/metadata.html
pwa/templates/pwa/pwa_offline.html
pwa/templatetags/__init__.py
pwa/templatetags/pwa.py
pwa/templatetags/__pycache__/__init__.cpython-39.pyc
pwa/templatetags/__pycache__/pwa.cpython-39.pyc
django_simple_pwa-2.2.1.dist-info/LICENSE
django_simple_pwa-2.2.1.dist-info/METADATA
django_simple_pwa-2.2.1.dist-info/WHEEL
django_simple_pwa-2.2.1.dist-info/top_level.txt
django_simple_pwa-2.2.1.dist-info/RECORD
